kiarina/lib/redisearch/__init__.py
kiarina/lib/redisearch/_settings.py
kiarina/lib/redisearch/asyncio.py
kiarina/lib/redisearch/py.typed
kiarina/lib/redisearch/_async/__init__.py
kiarina/lib/redisearch/_async/helpers/__init__.py
kiarina/lib/redisearch/_async/helpers/create_redisearch_client.py
kiarina/lib/redisearch/_async/models/__init__.py
kiarina/lib/redisearch/_async/models/redisearch_client.py
kiarina/lib/redisearch/_core/__init__.py
kiarina/lib/redisearch/_core/operations/__init__.py
kiarina/lib/redisearch/_core/operations/count.py
kiarina/lib/redisearch/_core/operations/create_index.py
kiarina/lib/redisearch/_core/operations/delete.py
kiarina/lib/redisearch/_core/operations/drop_index.py
kiarina/lib/redisearch/_core/operations/exists_index.py
kiarina/lib/redisearch/_core/operations/find.py
kiarina/lib/redisearch/_core/operations/get.py
kiarina/lib/redisearch/_core/operations/get_info.py
kiarina/lib/redisearch/_core/operations/get_key.py
kiarina/lib/redisearch/_core/operations/migrate_index.py
kiarina/lib/redisearch/_core/operations/parse_search_result.py
kiarina/lib/redisearch/_core/operations/reset_index.py
kiarina/lib/redisearch/_core/operations/search.py
kiarina/lib/redisearch/_core/operations/set.py
kiarina/lib/redisearch/_core/schemas/__init__.py
kiarina/lib/redisearch/_core/schemas/document.py
kiarina/lib/redisearch/_core/schemas/redisearch_context.py
kiarina/lib/redisearch/_core/utils/__init__.py
kiarina/lib/redisearch/_core/utils/calc_score.py
kiarina/lib/redisearch/_core/utils/marshal_mappings.py
kiarina/lib/redisearch/_core/utils/unmarshal_mappings.py
kiarina/lib/redisearch/_core/views/__init__.py
kiarina/lib/redisearch/_core/views/info_result.py
kiarina/lib/redisearch/_core/views/search_result.py
kiarina/lib/redisearch/_sync/__init__.py
kiarina/lib/redisearch/_sync/helpers/__init__.py
kiarina/lib/redisearch/_sync/helpers/create_redisearch_client.py
kiarina/lib/redisearch/_sync/models/__init__.py
kiarina_lib_redisearch-1.35.0.dist-info/METADATA
kiarina_lib_redisearch-1.35.0.dist-info/WHEEL
kiarina_lib_redisearch-1.35.0.dist-info/RECORD
