Metadata-Version: 2.4
Name: kiarina-lib-redisearch
Version: 1.35.0
Summary: RediSearch client library for kiarina namespace
Project-URL: Homepage, https://github.com/kiarina/kiarina-python
Project-URL: Repository, https://github.com/kiarina/kiarina-python
Project-URL: Issues, https://github.com/kiarina/kiarina-python/issues
Project-URL: Changelog, https://github.com/kiarina/kiarina-python/blob/main/packages/kiarina-lib-redisearch/CHANGELOG.md
Project-URL: Documentation, https://github.com/kiarina/kiarina-python/tree/main/packages/kiarina-lib-redisearch#readme
Author-email: kiarina <kiarinadawa@gmail.com>
Maintainer-email: kiarina <kiarinadawa@gmail.com>
License-Expression: MIT
Keywords: database,fulltext,pydantic,redis,redisearch,search,settings,vector
Classifier: Development Status :: 4 - Beta
Classifier: Intended Audience :: Developers
Classifier: Operating System :: OS Independent
Classifier: Programming Language :: Python :: 3
Classifier: Programming Language :: Python :: 3.12
Classifier: Programming Language :: Python :: 3.13
Classifier: Topic :: Database
Classifier: Topic :: Internet :: WWW/HTTP :: Indexing/Search
Classifier: Topic :: Scientific/Engineering :: Artificial Intelligence
Classifier: Topic :: Software Development :: Libraries :: Python Modules
Classifier: Typing :: Typed
Requires-Python: >=3.12
Requires-Dist: numpy>=2.3.2
Requires-Dist: pydantic-settings-manager>=2.3.0
Requires-Dist: pydantic-settings>=2.10.1
Requires-Dist: pydantic>=2.11.7
Requires-Dist: redis>=6.4.0
